ups_sdk/__init__.py
ups_sdk/main.py
ups_sdk/test.py
ups_sdk/models/AccessRequest.py
ups_sdk/models/ActivityItem.py
ups_sdk/models/ActivityLocation.py
ups_sdk/models/Address.py
ups_sdk/models/Message.py
ups_sdk/models/Package.py
ups_sdk/models/PackageWeight.py
ups_sdk/models/ReferenceNumber.py
ups_sdk/models/ReferenceNumberItem.py
ups_sdk/models/Response.py
ups_sdk/models/Service.py
ups_sdk/models/ShipTo.py
ups_sdk/models/Shipment.py
ups_sdk/models/ShipmentWeight.py
ups_sdk/models/Shipper.py
ups_sdk/models/Status.py
ups_sdk/models/StatusCode.py
ups_sdk/models/StatusType.py
ups_sdk/models/TrackError.py
ups_sdk/models/TrackRequest.py
ups_sdk/models/TrackResponse.py
ups_sdk/models/TrackType.py
ups_sdk/models/TransactionReference.py
ups_sdk/models/UnitOfMeasurement.py
ups_sdk/models/__init__.py
ups_sdk-1.3.2.dist-info/LICENSE
ups_sdk-1.3.2.dist-info/METADATA
ups_sdk-1.3.2.dist-info/WHEEL
ups_sdk-1.3.2.dist-info/top_level.txt
ups_sdk-1.3.2.dist-info/RECORD
