Metadata-Version: 2.1
Name: ups-sdk
Version: 1.3.2
Summary: UPS Sdk
Author: Esat Yılmaz
Author-email: esatyilmaz3500@gmail.com
Classifier: Development Status :: 1 - Planning
Classifier: Topic :: Utilities
Classifier: Programming Language :: Python :: 3.9
License-File: LICENSE
